followee_notifier/__init__.py
followee_notifier/cli.py
followee_notifier/db.py
followee_notifier/notify/smtp.py
followee_notifier/notify/telegram.py
followee_notifier/platforms/__init__.py
followee_notifier/platforms/bilibili.py
followee_notifier/platforms/fake.py
followee_notifier/platforms/twitter.py
followee_notifier/types.py
followee_notifier-0.0.1a0.dist-info/METADATA
followee_notifier-0.0.1a0.dist-info/WHEEL
followee_notifier-0.0.1a0.dist-info/entry_points.txt
followee_notifier-0.0.1a0.dist-info/RECORD
